orpheus_r/__init__.py
orpheus_r/environments/asr_correctness/asr_correctness.py
orpheus_r/utils/utils.py
orpheus_r-0.1.4.dist-info/METADATA
orpheus_r-0.1.4.dist-info/WHEEL
orpheus_r-0.1.4.dist-info/top_level.txt
orpheus_r-0.1.4.dist-info/RECORD
